abin_add_two_num/__init__.py
abin_add_two_num-0.1.2.dist-info/METADATA
abin_add_two_num-0.1.2.dist-info/WHEEL
abin_add_two_num-0.1.2.dist-info/entry_points.txt
abin_add_two_num-0.1.2.dist-info/RECORD
