Metadata-Version: 2.4
Name: abin-add-two-num
Version: 0.1.2
Summary: Add your description here
Author-email: Abin <trashwbin@gmail.com>
Requires-Python: >=3.12
Requires-Dist: fastmcp>=2.10.5
Requires-Dist: mcp[cli]>=1.11.0
